nexusformat/__init__.py
nexusformat/_version.py
nexusformat/definitions/nxdl.xsd
nexusformat/definitions/nxdlTypes.xsd
nexusformat/definitions/applications/NXapm.nxdl.xml
nexusformat/definitions/applications/NXarchive.nxdl.xml
nexusformat/definitions/applications/NXarpes.nxdl.xml
nexusformat/definitions/applications/NXcanSAS.nxdl.xml
nexusformat/definitions/applications/NXdirecttof.nxdl.xml
nexusformat/definitions/applications/NXellipsometry.nxdl.xml
nexusformat/definitions/applications/NXfluo.nxdl.xml
nexusformat/definitions/applications/NXindirecttof.nxdl.xml
nexusformat/definitions/applications/NXiqproc.nxdl.xml
nexusformat/definitions/applications/NXlauetof.nxdl.xml
nexusformat/definitions/applications/NXmonopd.nxdl.xml
nexusformat/definitions/applications/NXmpes.nxdl.xml
nexusformat/definitions/applications/NXmpes_arpes.nxdl.xml
nexusformat/definitions/applications/NXmx.nxdl.xml
nexusformat/definitions/applications/NXoptical_spectroscopy.nxdl.xml
nexusformat/definitions/applications/NXraman.nxdl.xml
nexusformat/definitions/applications/NXrefscan.nxdl.xml
nexusformat/definitions/applications/NXreftof.nxdl.xml
nexusformat/definitions/applications/NXsas.nxdl.xml
nexusformat/definitions/applications/NXsastof.nxdl.xml
nexusformat/definitions/applications/NXscan.nxdl.xml
nexusformat/definitions/applications/NXspe.nxdl.xml
nexusformat/definitions/applications/NXsqom.nxdl.xml
nexusformat/definitions/applications/NXstxm.nxdl.xml
nexusformat/definitions/applications/NXtas.nxdl.xml
nexusformat/definitions/applications/NXtofnpd.nxdl.xml
nexusformat/definitions/applications/NXtofraw.nxdl.xml
nexusformat/definitions/applications/NXtofsingle.nxdl.xml
nexusformat/definitions/applications/NXtomo.nxdl.xml
nexusformat/definitions/applications/NXtomophase.nxdl.xml
nexusformat/definitions/applications/NXtomoproc.nxdl.xml
nexusformat/definitions/applications/NXxas.nxdl.xml
nexusformat/definitions/applications/NXxasproc.nxdl.xml
nexusformat/definitions/applications/NXxbase.nxdl.xml
nexusformat-2.0.0.dist-info/licenses/COPYING
nexusformat-2.0.0.dist-info/METADATA
nexusformat-2.0.0.dist-info/WHEEL
nexusformat-2.0.0.dist-info/entry_points.txt
nexusformat-2.0.0.dist-info/pbr.json
nexusformat-2.0.0.dist-info/top_level.txt
nexusformat-2.0.0.dist-info/RECORD
