Metadata-Version: 2.4
Name: nexusformat
Version: 2.0.0
Summary: Python API to access NeXus data
Author-email: Raymond Osborn <rayosborn@mac.com>
License: Licensing Terms for NeXpy
Project-URL: Homepage, https://nexpy.github.io/nexpy
Project-URL: Repository, https://github.com/nexpy/nexusformat.git
Project-URL: Issues, https://github.com/nexpy/nexusformat/issues
Project-URL: Documentation, https://nexpy.github.io/nexpy/pythonshell.html
Project-URL: Changelog, https://github.com/nexpy/nexusformat/releases
Keywords: data format,HDF5,neutron scattering,x-ray scattering
Classifier: Development Status :: 5 - Production/Stable
Classifier: License :: OSI Approved :: BSD License
Classifier: Intended Audience :: Developers
Classifier: Intended Audience :: Science/Research
Classifier: Topic :: Scientific/Engineering
Classifier: Programming Language :: Python :: 3
Classifier: Programming Language :: Python :: 3.9
Classifier: Programming Language :: Python :: 3.10
Classifier: Programming Language :: Python :: 3.11
Classifier: Programming Language :: Python :: 3.12
Classifier: Programming Language :: Python :: 3.13
Classifier: Topic :: Scientific/Engineering
Classifier: Topic :: Scientific/Engineering :: Visualization
Requires-Python: >=3.9
License-File: COPYING
Requires-Dist: colored
Requires-Dist: h5py
Requires-Dist: hdf5plugin
Requires-Dist: numpy
Requires-Dist: packaging
Requires-Dist: pygments
Requires-Dist: python-dateutil
Requires-Dist: scipy
Requires-Dist: importlib_resources; python_version <= "3.9"
Provides-Extra: testing
Requires-Dist: pytest; extra == "testing"
Dynamic: license-file
